dbl_main/__init__.py
dbl_main/state_projection.py
dbl_main-0.3.0.dist-info/licenses/LICENSE
dbl_main-0.3.0.dist-info/METADATA
dbl_main-0.3.0.dist-info/WHEEL
dbl_main-0.3.0.dist-info/top_level.txt
dbl_main-0.3.0.dist-info/RECORD
