Metadata-Version: 2.4
Name: dbl-main
Version: 0.3.0
Summary: Deterministic Boundary Layer - projection layer on dbl-core
Author-email: Lukas Pfister <228201683+lukaspfisterch@users.noreply.github.com>
License: MIT
Project-URL: Repository, https://github.com/lukaspfisterch/dbl-main
Project-URL: Issues, https://github.com/lukaspfisterch/dbl-main/issues
Keywords: dbl,governance,policy,llm,orchestration,deterministic
Classifier: Development Status :: 2 - Pre-Alpha
Classifier: Intended Audience :: Developers
Classifier: License :: OSI Approved :: MIT License
Classifier: Programming Language :: Python :: 3.11
Classifier: Programming Language :: Python :: 3.12
Classifier: Typing :: Typed
Requires-Python: >=3.11
License-File: LICENSE
Requires-Dist: dbl-core>=0.3.0
Provides-Extra: test
Requires-Dist: pytest>=8.0.0; extra == "test"
Provides-Extra: test-fuzz
Requires-Dist: pytest>=8.0.0; extra == "test-fuzz"
Requires-Dist: hypothesis>=6.0.0; extra == "test-fuzz"
Provides-Extra: yaml
Requires-Dist: pyyaml>=6.0.0; extra == "yaml"
Provides-Extra: dev
Requires-Dist: pytest>=8.0.0; extra == "dev"
Requires-Dist: hypothesis>=6.0.0; extra == "dev"
Requires-Dist: pyyaml>=6.0.0; extra == "dev"
Dynamic: license-file
